pal.cpython-312-darwin.so
raudio/raudio.c
pyaudiolib-0.0.1.dist-info/LICENSE
pyaudiolib-0.0.1.dist-info/METADATA
pyaudiolib-0.0.1.dist-info/WHEEL
pyaudiolib-0.0.1.dist-info/top_level.txt
pyaudiolib-0.0.1.dist-info/RECORD
