Metadata-Version: 2.2
Name: pyaudiolib
Version: 0.0.1
Summary: Python Audio Library (raudio bindings)
Home-page: https://github.com/takeiteasy/pal
Author: George Watson
Author-email: George Watson <gigolo@hotmail.co.uk>
Project-URL: Homepage, https://github.com/takeiteasy/pal
Project-URL: Issues, https://github.com/takeiteasy/pal/issues
Classifier: Programming Language :: Python :: 3
Classifier: License :: OSI Approved :: MIT License
Classifier: Operating System :: OS Independent
Requires-Python: >=3.8
License-File: LICENSE
Dynamic: author
Dynamic: home-page
